LICENSE.txt
MANIFEST.in
Makefile
README.md
pytest.ini
setup.py
django_perseus/__init__.py
django_perseus/exceptions.py
django_perseus/utils.py
django_perseus.egg-info/.DS_Store
django_perseus.egg-info/PKG-INFO
django_perseus.egg-info/SOURCES.txt
django_perseus.egg-info/dependency_links.txt
django_perseus.egg-info/requires.txt
django_perseus.egg-info/top_level.txt
django_perseus/importers/__init__.py
django_perseus/importers/base.py
django_perseus/management/__init__.py
django_perseus/management/commands/__init__.py
django_perseus/management/commands/render.py
django_perseus/renderers/__init__.py
django_perseus/renderers/base.py
django_perseus/renderers/default.py
django_perseus/templatetags/__init__.py
django_perseus/templatetags/django_perseus_tags.py
django_perseus/tests/__init__.py
django_perseus/tests/settings.py
django_perseus/tests/test_commands.py
django_perseus/tests/test_importers.py
django_perseus/tests/test_renderers.py
django_perseus/tests/test_templatetags.py
django_perseus/tests/test_utils.py
django_perseus/tests/urls.py
django_perseus/tests/utils.py
django_perseus/tests/testapp1/__init__.py
django_perseus/tests/testapp1/models.py
django_perseus/tests/testapp2/__init__.py
django_perseus/tests/testapp2/importers.py
django_perseus/tests/testapp2/models.py
django_perseus/tests/testapp2/renderers.py
django_perseus/tests/testapp2/urls.py
django_perseus/tests/testapp2/views.py
docs/.DS_Store
docs/Makefile
docs/make.bat
docs/source/conf.py
docs/source/index.rst
docs/source/installation.rst
docs/source/usage.rst