Metadata-Version: 1.1
Name: django-perseus
Version: 0.1.1
Summary: Builds a static version of your Django website
Home-page: https://github.com/lockwooddev/django-perseus
Author: Carlo Smouter
Author-email: lockwooddev@gmail.com
License: MIT
Keywords: django static html
Platform: UNKNOWN
Classifier: Development Status :: 4 - Beta
Classifier: License :: OSI Approved :: MIT License
Classifier: Operating System :: OS Independent
Classifier: Programming Language :: Python :: 2.7
Classifier: Topic :: Software Development :: Libraries :: Python Modules
